README.rst
setup.cfg
setup.py
pingo/__init__.py
pingo/board.py
pingo/util.py
pingo.egg-info/PKG-INFO
pingo.egg-info/SOURCES.txt
pingo.egg-info/dependency_links.txt
pingo.egg-info/top_level.txt
pingo/arduino/__init__.py
pingo/arduino/arduino.py
pingo/arduino/tests/__init__.py
pingo/arduino/tests/test_arduino.py
pingo/bbb/__init__.py
pingo/bbb/bbb.py
pingo/bbb/tests/__init__.py
pingo/bbb/tests/test_bbb.py
pingo/detect/__init__.py
pingo/detect/detect.py
pingo/detect/tests/__init__.py
pingo/detect/tests/test_detect.py
pingo/ghost/__init__.py
pingo/ghost/ghost.py
pingo/ghost/tests/__init__.py
pingo/ghost/tests/test_ghost.py
pingo/pcduino/__init__.py
pingo/pcduino/pcduino.py
pingo/pcduino/tests/__init__.py
pingo/pcduino/tests/test_pcduino.py
pingo/pinGUIm/__init__.py
pingo/pinGUIm/pinGUIm.py
pingo/rpi/__init__.py
pingo/rpi/rpi.py
pingo/rpi/spi/__init__.py
pingo/rpi/spi/mcp3008.py
pingo/rpi/tests/__init__.py
pingo/rpi/tests/test_rpi.py
pingo/test/__init__.py
pingo/test/level0/__init__.py
pingo/test/level0/cases.py
pingo/test/level1/__init__.py
pingo/test/level1/cases.py
pingo/udoo/__init__.py
pingo/udoo/udoo.py
pingo/udoo/tests/__init__.py
pingo/udoo/tests/test_udoo.py